pygl_astroids/__init__.py
pygl_astroids/__main__.py
pygl_astroids/asteroid.py
pygl_astroids/bullet.py
pygl_astroids/globaldefs.py
pygl_astroids/globalvars.py
pygl_astroids/labels.py
pygl_astroids/player.py
pygl_astroids/vector.py
PyGL_Astroids-0.0.3.dist-info/LICENSE
PyGL_Astroids-0.0.3.dist-info/METADATA
PyGL_Astroids-0.0.3.dist-info/WHEEL
PyGL_Astroids-0.0.3.dist-info/top_level.txt
PyGL_Astroids-0.0.3.dist-info/RECORD
